{
  "uid": "the_orchestrator",
  "type": "app",
  "config": {
    "description": "GTM automation orchestrator - LinkedIn outreach, data enrichment, and treatment protocols",
    "name": "The Orchestrator",
    "distribution": "private",
    "auth": {
      "type": "static",
      "requiredScopes": [
        "oauth",
        "crm.objects.contacts.read",
        "crm.objects.contacts.write",
        "crm.objects.companies.read",
        "crm.objects.companies.write",
        "crm.lists.read",
        "crm.objects.owners.read"
      ]
    },
    "permittedUrls": {
      "fetch": ["https://gtmorchestrator.netlify.app"],
      "iframe": [],
      "img": ["https://media.licdn.com"]
    },
    "support": {
      "supportEmail": "support@example.com",
      "documentationUrl": "https://example.com/docs",
      "supportUrl": "https://example.com/support",
      "supportPhone": "+18005555555"
    }
  }
}
